robodbg/__init__.py
robodbg/dbg.cp312-win32.pyd
robodbg/debugger.py
robodbg-0.0.2.dist-info/licenses/LICENSE.TXT
robodbg-0.0.2.dist-info/METADATA
robodbg-0.0.2.dist-info/WHEEL
robodbg-0.0.2.dist-info/top_level.txt
robodbg-0.0.2.dist-info/RECORD
